dicomUtils/__init__.py
dicomUtils/dicom3D.py
dicomUtils/misc.py
dicomUtils/multiframe.py
dicomUtils/padorcut.py
dicomUtils/resources/__init__.py
dicomUtils/resources/runtime_dependencies.cfg
dicomUtils/ui/__init__.py
dicomUtils/ui/pyDicomCircleROI.py
dicomUtils/ui/pyDicomView.py
dafne_dicomUtils-0.1.7.dist-info/LICENSE
dafne_dicomUtils-0.1.7.dist-info/METADATA
dafne_dicomUtils-0.1.7.dist-info/WHEEL
dafne_dicomUtils-0.1.7.dist-info/entry_points.txt
dafne_dicomUtils-0.1.7.dist-info/top_level.txt
dafne_dicomUtils-0.1.7.dist-info/RECORD
