Metadata-Version: 2.1
Name: dafne-dicomUtils
Version: 0.1.7
Summary: A package for DICOM utilities
Home-page: https://github.com/dafne-imaging/dafne-dicomUtils
Author: Dafne-Imaging Team
Author-email: francesco.santini@unibas.ch
Classifier: Programming Language :: Python :: 3
Classifier: License :: OSI Approved :: Apache Software License
Classifier: Operating System :: OS Independent
Requires-Python: >=3.6
License-File: LICENSE
Requires-Dist: numpy
Requires-Dist: scipy
Requires-Dist: matplotlib
Requires-Dist: pydicom>=2.2.0
Requires-Dist: ormir-pyvoxel
Requires-Dist: qtpy
Requires-Dist: progress
Requires-Dist: flexidep>=0.0.8
